<?xml version="1.0" encoding="UTF-8"?><record_update>
    <sys_dictionary action="DELETE" element="age" table="x_1067582_rco_rcotesting">
        <active>true</active>
        <array>false</array>
        <attributes/>
        <audit>false</audit>
        <calculation/>
        <choice>0</choice>
        <choice_field/>
        <choice_table/>
        <column_label>Age</column_label>
        <comments/>
        <create_roles/>
        <default_value/>
        <defaultsort/>
        <delete_roles/>
        <dependent/>
        <dependent_on_field/>
        <display>false</display>
        <dynamic_creation>false</dynamic_creation>
        <dynamic_creation_script/>
        <dynamic_default_value/>
        <dynamic_ref_qual/>
        <element>age</element>
        <element_reference>false</element_reference>
        <foreign_database/>
        <formula/>
        <function_definition/>
        <function_field>false</function_field>
        <internal_type display_value="String">string</internal_type>
        <mandatory>false</mandatory>
        <max_length>40</max_length>
        <name>x_1067582_rco_rcotesting</name>
        <next_element/>
        <primary>false</primary>
        <read_only>false</read_only>
        <read_roles/>
        <reference/>
        <reference_cascade_rule/>
        <reference_floats>false</reference_floats>
        <reference_key/>
        <reference_qual/>
        <reference_qual_condition/>
        <reference_type/>
        <spell_check>false</spell_check>
        <staged>false</staged>
        <sys_class_name>sys_dictionary</sys_class_name>
        <sys_created_by>admin</sys_created_by>
        <sys_created_on>2023-08-16 12:14:34</sys_created_on>
        <sys_id>ab49937747e4311090954c6d826d43f8</sys_id>
        <sys_name>Age</sys_name>
        <sys_package display_value="RCO" source="x_1067582_rco">9c06caa14764311090954c6d826d43b9</sys_package>
        <sys_policy/>
        <sys_scope display_value="RCO">9c06caa14764311090954c6d826d43b9</sys_scope>
        <sys_update_name>sys_dictionary_x_1067582_rco_rcotesting_age</sys_update_name>
        <sys_updated_by>admin</sys_updated_by>
        <sys_updated_on>2023-08-17 05:06:31</sys_updated_on>
        <table_reference>false</table_reference>
        <text_index>false</text_index>
        <unique>false</unique>
        <use_dependent_field>false</use_dependent_field>
        <use_dynamic_default>false</use_dynamic_default>
        <use_reference_qualifier>simple</use_reference_qualifier>
        <virtual>false</virtual>
        <virtual_type>script</virtual_type>
        <widget/>
        <write_roles/>
        <xml_view>false</xml_view>
    </sys_dictionary>
    <sys_update_version action="INSERT_OR_UPDATE">
        <action>DELETE</action>
        <application display_value="RCO">9c06caa14764311090954c6d826d43b9</application>
        <file_path/>
        <instance_id>895d6f0bdb64dfc03353f22ebf961959</instance_id>
        <instance_name>dev51591</instance_name>
        <name>sys_dictionary_x_1067582_rco_rcotesting_age</name>
        <payload><![CDATA[<?xml version="1.0" encoding="UTF-8"?><record_update><sys_dictionary action="INSERT_OR_UPDATE" element="age" table="x_1067582_rco_rcotesting"><active>true</active><array>false</array><attributes/><audit>false</audit><calculation/><choice>0</choice><choice_field/><choice_table/><column_label>Age</column_label><comments/><create_roles/><default_value/><defaultsort/><delete_roles/><dependent/><dependent_on_field/><display>false</display><dynamic_creation>false</dynamic_creation><dynamic_creation_script/><dynamic_default_value/><dynamic_ref_qual/><element>age</element><element_reference>false</element_reference><foreign_database/><formula/><function_definition/><function_field>false</function_field><internal_type display_value="String">string</internal_type><mandatory>false</mandatory><max_length>40</max_length><name>x_1067582_rco_rcotesting</name><next_element/><primary>false</primary><read_only>false</read_only><read_roles/><reference/><reference_cascade_rule/><reference_floats>false</reference_floats><reference_key/><reference_qual/><reference_qual_condition/><reference_type/><spell_check>false</spell_check><staged>false</staged><sys_class_name>sys_dictionary</sys_class_name><sys_created_by>admin</sys_created_by><sys_created_on>2023-08-16 12:14:34</sys_created_on><sys_id>ab49937747e4311090954c6d826d43f8</sys_id><sys_name>Age</sys_name><sys_package display_value="RCO" source="x_1067582_rco">9c06caa14764311090954c6d826d43b9</sys_package><sys_policy/><sys_scope display_value="RCO">9c06caa14764311090954c6d826d43b9</sys_scope><sys_update_name>sys_dictionary_x_1067582_rco_rcotesting_age</sys_update_name><sys_updated_by>admin</sys_updated_by><sys_updated_on>2023-08-17 05:06:31</sys_updated_on><table_reference>false</table_reference><text_index>false</text_index><unique>false</unique><use_dependent_field>false</use_dependent_field><use_dynamic_default>false</use_dynamic_default><use_reference_qualifier>simple</use_reference_qualifier><virtual>false</virtual><virtual_type>script</virtual_type><widget/><write_roles/><xml_view>false</xml_view></sys_dictionary></record_update>]]></payload>
        <payload_hash>-1635459259</payload_hash>
        <record_name>rcotesting.Age</record_name>
        <reverted_from/>
        <source>9c06caa14764311090954c6d826d43bb</source>
        <source_table>sys_update_set</source_table>
        <state>previous</state>
        <sys_created_by>admin</sys_created_by>
        <sys_created_on>2023-08-17 05:06:31</sys_created_on>
        <sys_id>c7e083c04734711090954c6d826d43d9</sys_id>
        <sys_mod_count>0</sys_mod_count>
        <sys_recorded_at>18a01e359950000001</sys_recorded_at>
        <sys_updated_by>admin</sys_updated_by>
        <sys_updated_on>2023-08-17 05:06:31</sys_updated_on>
        <type>Dictionary</type>
        <update_guid>03e083c054347110fca40a1e8e208fd9</update_guid>
        <update_guid_history>03e083c054347110fca40a1e8e208fd9:-1635459259,c7e083c0c73471100dae47f62c07bbc6:1692486834,b749d377c9e431106335ca9dd6256765:-1635459259,7749d377efe431109b37b05a3a35950a:1732259778,ee285ff3d2e431109ec2a190ba4c2e0d:-1148509423,77b39a336fa03110f761073b0a813a45:-914382011,73b39a33e2a031102d8fe04d39adeb3d:-1635459259,e7b35a33ada031109aba62fcfb189063:1732259778</update_guid_history>
    </sys_update_version>
    <sys_metadata_delete action="INSERT_OR_UPDATE">
        <sys_audit_delete/>
        <sys_class_name>sys_metadata_delete</sys_class_name>
        <sys_created_by>admin</sys_created_by>
        <sys_created_on>2023-10-11 06:45:07</sys_created_on>
        <sys_db_object display_value="" name="sys_dictionary">sys_dictionary</sys_db_object>
        <sys_id>0aec9b1a542e421081f6809b2c105024</sys_id>
        <sys_metadata>ab49937747e4311090954c6d826d43f8</sys_metadata>
        <sys_mod_count>0</sys_mod_count>
        <sys_name>Age</sys_name>
        <sys_package display_value="RCO" source="x_1067582_rco">9c06caa14764311090954c6d826d43b9</sys_package>
        <sys_parent display_value="">3b58933747e4311090954c6d826d433a</sys_parent>
        <sys_policy/>
        <sys_scope display_value="RCO">9c06caa14764311090954c6d826d43b9</sys_scope>
        <sys_scope_delete display_value="">0d7e648ec1ba41a482ecd8d90b47e610</sys_scope_delete>
        <sys_update_name>sys_dictionary_x_1067582_rco_rcotesting_age</sys_update_name>
        <sys_update_version display_value="sys_dictionary_x_1067582_rco_rcotesting_age">c7e083c04734711090954c6d826d43d9</sys_update_version>
        <sys_updated_by>admin</sys_updated_by>
        <sys_updated_on>2023-10-11 06:45:07</sys_updated_on>
    </sys_metadata_delete>
</record_update>
